pyunitx/__init__.py
pyunitx/_api.py
pyunitx/_exceptions.py
pyunitx/angle.py
pyunitx/area.py
pyunitx/capacitance.py
pyunitx/charge.py
pyunitx/constants.py
pyunitx/current.py
pyunitx/data.py
pyunitx/derived.py
pyunitx/energy.py
pyunitx/force.py
pyunitx/frequency.py
pyunitx/inductance.py
pyunitx/length.py
pyunitx/luminosity.py
pyunitx/magneticflux.py
pyunitx/magneticfluxdensity.py
pyunitx/mass.py
pyunitx/mole.py
pyunitx/power.py
pyunitx/pressure.py
pyunitx/resistance.py
pyunitx/resistor.py
pyunitx/temperature.py
pyunitx/time.py
pyunitx/uconvert.py
pyunitx/voltage.py
pyunitx/volume.py
pyunitx-0.10.2.dist-info/LICENSE
pyunitx-0.10.2.dist-info/METADATA
pyunitx-0.10.2.dist-info/WHEEL
pyunitx-0.10.2.dist-info/entry_points.txt
pyunitx-0.10.2.dist-info/RECORD
