Metadata-Version: 2.3
Name: pyunitx
Version: 0.10.2
Summary: First-class manipulation of physical quantities
License: GPL-3.0-or-later
Author: Nick Thurmes
Author-email: nthurmes@gmail.com
Requires-Python: >=3.7,<4.0
Classifier: License :: OSI Approved :: GNU General Public License v3 or later (GPLv3+)
Classifier: Programming Language :: Python :: 3
Classifier: Programming Language :: Python :: 3.7
Classifier: Programming Language :: Python :: 3.8
Classifier: Programming Language :: Python :: 3.9
Classifier: Programming Language :: Python :: 3.10
Classifier: Programming Language :: Python :: 3.11
Classifier: Programming Language :: Python :: 3.12
Classifier: Programming Language :: Python :: 3.13
Provides-Extra: docs
Requires-Dist: pypandoc (>=1.9,<2.0) ; extra == "docs"
Requires-Dist: sigfig (>=1.3.2,<2.0.0)
